identory/__init__.py
identory/client.py
identory/exceptions.py
identory/groups.py
identory/presets.py
identory/profiles.py
identory/settings.py
identory/status.py
identory/tools.py
identory-0.1.5.dist-info/licenses/LICENSE
identory-0.1.5.dist-info/METADATA
identory-0.1.5.dist-info/WHEEL
identory-0.1.5.dist-info/top_level.txt
identory-0.1.5.dist-info/RECORD
