Metadata-Version: 2.4
Name: identory
Version: 0.1.5
Summary: Python Wrapper for the Identory browser automation platform
Author-email: Okoya Usman <usmanokoya10@gmail.com>
Maintainer-email: Okoya Usman <usmanokoya10@gmail.com>
License: MIT
Project-URL: Homepage, https://identory.com
Project-URL: Repository, https://github.com/okoyausman/identory-python-wrapper
Project-URL: Issues, https://github.com/okoyausman/identory-python-wrapper/issues
Keywords: identory,browser,automation,selenium,pyppeteer,playwright,puppeteer,proxy,anti-detection,fingerprinting,api,sdk,wrapper
Requires-Python: >=3.8
License-File: LICENSE
Requires-Dist: requests>=2.25.0
Dynamic: license-file
